blockhouse/__init__.py
blockhouse/client.py
blockhouse/exceptions.py
blockhouse/s3_connector.py
blockhouse/usage.py
tests/__init__.py
tests/test_client.py
blockhousesdk-0.1.1.dist-info/METADATA
blockhousesdk-0.1.1.dist-info/WHEEL
blockhousesdk-0.1.1.dist-info/top_level.txt
blockhousesdk-0.1.1.dist-info/RECORD
