Metadata-Version: 2.1
Name: blockhousesdk
Version: 0.1.1
Summary: A Python SDK for Blockhouse to transfer files
Author: Zubair
Author-email: zubair.flexlab@gmail.com
Classifier: Programming Language :: Python :: 3
Classifier: License :: OSI Approved :: MIT License
Classifier: Operating System :: OS Independent
Requires-Python: >=3.6
Requires-Dist: boto3
